generated/Top.sv
// Generated by CIRCT firtool-1.62.0
// Standard header to adapt well known macros for register randomization.
`ifndef RANDOMIZE
  `ifdef RANDOMIZE_REG_INIT
    `define RANDOMIZE
  `endif // RANDOMIZE_REG_INIT
`endif // not def RANDOMIZE

// RANDOM may be set to an expression that produces a 32-bit random unsigned value.
`ifndef RANDOM
  `define RANDOM $random
`endif // not def RANDOM

// Users can define INIT_RANDOM as general code that gets injected into the
// initializer block for modules with registers.
`ifndef INIT_RANDOM
  `define INIT_RANDOM
`endif // not def INIT_RANDOM

// If using random initialization, you can also define RANDOMIZE_DELAY to
// customize the delay used, otherwise 0.002 is used.
`ifndef RANDOMIZE_DELAY
  `define RANDOMIZE_DELAY 0.002
`endif // not def RANDOMIZE_DELAY

// Define INIT_RANDOM_PROLOG_ for use in our modules below.
`ifndef INIT_RANDOM_PROLOG_
  `ifdef RANDOMIZE
    `ifdef VERILATOR
      `define INIT_RANDOM_PROLOG_ `INIT_RANDOM
    `else  // VERILATOR
      `define INIT_RANDOM_PROLOG_ `INIT_RANDOM #`RANDOMIZE_DELAY begin end
    `endif // VERILATOR
  `else  // RANDOMIZE
    `define INIT_RANDOM_PROLOG_
  `endif // RANDOMIZE
`endif // not def INIT_RANDOM_PROLOG_

// Include register initializers in init blocks unless synthesis is set
`ifndef SYNTHESIS
  `ifndef ENABLE_INITIAL_REG_
    `define ENABLE_INITIAL_REG_
  `endif // not def ENABLE_INITIAL_REG_
`endif // not def SYNTHESIS

// Include rmemory initializers in init blocks unless synthesis is set
`ifndef SYNTHESIS
  `ifndef ENABLE_INITIAL_MEM_
    `define ENABLE_INITIAL_MEM_
  `endif // not def ENABLE_INITIAL_MEM_
`endif // not def SYNTHESIS

module Top(	// src/main/scala/led/led.scala:10:7
  input         clock,	// src/main/scala/led/led.scala:10:7
                reset,	// src/main/scala/led/led.scala:10:7
  output [15:0] io_y	// src/main/scala/led/led.scala:11:16
);

  reg [31:0] count;	// src/main/scala/led/led.scala:15:24
  always @(posedge clock) begin	// src/main/scala/led/led.scala:10:7
    if (reset)	// src/main/scala/led/led.scala:10:7
      count <= 32'h0;	// src/main/scala/led/led.scala:15:24
    else if (count == 32'h7A120)	// src/main/scala/led/led.scala:15:24, :19:16
      count <= 32'h0;	// src/main/scala/led/led.scala:15:24
    else	// src/main/scala/led/led.scala:19:16
      count <= count + 32'h1;	// src/main/scala/led/led.scala:15:24, :17:20
  end // always @(posedge)
  `ifdef ENABLE_INITIAL_REG_	// src/main/scala/led/led.scala:10:7
    `ifdef FIRRTL_BEFORE_INITIAL	// src/main/scala/led/led.scala:10:7
      `FIRRTL_BEFORE_INITIAL	// src/main/scala/led/led.scala:10:7
    `endif // FIRRTL_BEFORE_INITIAL
    initial begin	// src/main/scala/led/led.scala:10:7
      automatic logic [31:0] _RANDOM[0:0];	// src/main/scala/led/led.scala:10:7
      `ifdef INIT_RANDOM_PROLOG_	// src/main/scala/led/led.scala:10:7
        `INIT_RANDOM_PROLOG_	// src/main/scala/led/led.scala:10:7
      `endif // INIT_RANDOM_PROLOG_
      `ifdef RANDOMIZE_REG_INIT	// src/main/scala/led/led.scala:10:7
        _RANDOM[/*Zero width*/ 1'b0] = `RANDOM;	// src/main/scala/led/led.scala:10:7
        count = _RANDOM[/*Zero width*/ 1'b0];	// src/main/scala/led/led.scala:10:7, :15:24
      `endif // RANDOMIZE_REG_INIT
    end // initial
    `ifdef FIRRTL_AFTER_INITIAL	// src/main/scala/led/led.scala:10:7
      `FIRRTL_AFTER_INITIAL	// src/main/scala/led/led.scala:10:7
    `endif // FIRRTL_AFTER_INITIAL
  `endif // ENABLE_INITIAL_REG_
  assign io_y = count[15:0];	// src/main/scala/led/led.scala:10:7, :15:24, :23:10
endmodule

logs/waveform.vcd
$version Generated by VerilatedVcd $end
$timescale 1ps $end

 $scope module TOP $end
  $var wire  1 # clock $end
  $var wire 16 % io_y [15:0] $end
  $var wire  1 $ reset $end
  $scope module Top $end
   $var wire  1 # clock $end
   $var wire 32 & count [31:0] $end
   $var wire 16 % io_y [15:0] $end
   $var wire  1 $ reset $end
  $upscope $end
 $upscope $end
$enddefinitions $end


#0
0#
1$
b0000000000000000 %
b00000000000000000000000000000000 &
#1
#2
1#
#3
0#
0$
#4
1#
b0000000000000001 %
b00000000000000000000000000000001 &
#5
0#
#6
1#
b0000000000000010 %
b00000000000000000000000000000010 &
#7
0#
#8
1#
b0000000000000011 %
b00000000000000000000000000000011 &
#9
0#
#10
1#
b0000000000000100 %
b00000000000000000000000000000100 &
#11
0#
#12
1#
b0000000000000101 %
b00000000000000000000000000000101 &
#13
0#
#14
1#
b0000000000000110 %
b00000000000000000000000000000110 &
#15
0#
#16
1#
b0000000000000111 %
b00000000000000000000000000000111 &
#17
0#
#18
1#
b0000000000001000 %
b00000000000000000000000000001000 &
#19
0#
#20
1#
b0000000000001001 %
b00000000000000000000000000001001 &
#21
0#
#22
1#
b0000000000001010 %
b00000000000000000000000000001010 &
#23
0#
#24
1#
b0000000000001011 %
b00000000000000000000000000001011 &
#25
0#
#26
1#
b0000000000001100 %
b00000000000000000000000000001100 &
#27
0#
#28
1#
b0000000000001101 %
b00000000000000000000000000001101 &
#29
0#
#30
1#
b0000000000001110 %
b00000000000000000000000000001110 &
#31
0#
#32
1#
b0000000000001111 %
b00000000000000000000000000001111 &
#33
0#
#34
1#
b0000000000010000 %
b00000000000000000000000000010000 &
#35
0#
#36
1#
b0000000000010001 %
b00000000000000000000000000010001 &
#37
0#
#38
1#
b0000000000010010 %
b00000000000000000000000000010010 &
#39
0#
#40
1#
b0000000000010011 %
b00000000000000000000000000010011 &
#41
0#
#42
1#
b0000000000010100 %
b00000000000000000000000000010100 &
#43
0#
#44
1#
b0000000000010101 %
b00000000000000000000000000010101 &
#45
0#
#46
1#
b0000000000010110 %
b00000000000000000000000000010110 &
#47
0#
#48
1#
b0000000000010111 %
b00000000000000000000000000010111 &
#49
0#
#50
1#
b0000000000011000 %
b00000000000000000000000000011000 &
#51
0#
#52
1#
b0000000000011001 %
b00000000000000000000000000011001 &
#53
0#
#54
1#
b0000000000011010 %
b00000000000000000000000000011010 &
#55
0#
#56
1#
b0000000000011011 %
b00000000000000000000000000011011 &
#57
0#
#58
1#
b0000000000011100 %
b00000000000000000000000000011100 &
#59
0#
#60
1#
b0000000000011101 %
b00000000000000000000000000011101 &
#61
0#
#62
1#
b0000000000011110 %
b00000000000000000000000000011110 &
#63
0#
#64
1#
b0000000000011111 %
b00000000000000000000000000011111 &
#65
0#
#66
1#
b0000000000100000 %
b00000000000000000000000000100000 &
#67
0#
#68
1#
b0000000000100001 %
b00000000000000000000000000100001 &
#69
0#
#70
1#
b0000000000100010 %
b00000000000000000000000000100010 &
#71
0#
#72
1#
b0000000000100011 %
b00000000000000000000000000100011 &
#73
0#
#74
1#
b0000000000100100 %
b00000000000000000000000000100100 &
#75
0#
#76
1#
b0000000000100101 %
b00000000000000000000000000100101 &
#77
0#
#78
1#
b0000000000100110 %
b00000000000000000000000000100110 &
#79
0#
#80
1#
b0000000000100111 %
b00000000000000000000000000100111 &
#81
0#
#82
1#
b0000000000101000 %
b00000000000000000000000000101000 &
#83
0#
#84
1#
b0000000000101001 %
b00000000000000000000000000101001 &
#85
0#
#86
1#
b0000000000101010 %
b00000000000000000000000000101010 &
#87
0#
#88
1#
b0000000000101011 %
b00000000000000000000000000101011 &
#89
0#
#90
1#
b0000000000101100 %
b00000000000000000000000000101100 &
#91
0#
#92
1#
b0000000000101101 %
b00000000000000000000000000101101 &
#93
0#
#94
1#
b0000000000101110 %
b00000000000000000000000000101110 &
#95
0#
#96
1#
b0000000000101111 %
b00000000000000000000000000101111 &
#97
0#
#98
1#
b0000000000110000 %
b00000000000000000000000000110000 &
#99
0#
#100
1#
b0000000000110001 %
b00000000000000000000000000110001 &
#101
0#
#102
1#
b0000000000110010 %
b00000000000000000000000000110010 &
#103
0#
#104
1#
b0000000000110011 %
b00000000000000000000000000110011 &
#105
0#
#106
1#
b0000000000110100 %
b00000000000000000000000000110100 &
#107
0#
#108
1#
b0000000000110101 %
b00000000000000000000000000110101 &
#109
0#
#110
1#
b0000000000110110 %
b00000000000000000000000000110110 &
#111
0#
#112
1#
b0000000000110111 %
b00000000000000000000000000110111 &
#113
0#
#114
1#
b0000000000111000 %
b00000000000000000000000000111000 &
#115
0#
#116
1#
b0000000000111001 %
b00000000000000000000000000111001 &
#117
0#
#118
1#
b0000000000111010 %
b00000000000000000000000000111010 &
#119
0#
#120
1#
b0000000000111011 %
b00000000000000000000000000111011 &
#121
0#
#122
1#
b0000000000111100 %
b00000000000000000000000000111100 &
#123
0#
#124
1#
b0000000000111101 %
b00000000000000000000000000111101 &
#125
0#
#126
1#
b0000000000111110 %
b00000000000000000000000000111110 &
#127
0#
#128
1#
b0000000000111111 %
b00000000000000000000000000111111 &
#129
0#
#130
1#
b0000000001000000 %
b00000000000000000000000001000000 &
#131
0#
#132
1#
b0000000001000001 %
b00000000000000000000000001000001 &
#133
0#
#134
1#
b0000000001000010 %
b00000000000000000000000001000010 &
#135
0#
#136
1#
b0000000001000011 %
b00000000000000000000000001000011 &
#137
0#
#138
1#
b0000000001000100 %
b00000000000000000000000001000100 &
#139
0#
#140
1#
b0000000001000101 %
b00000000000000000000000001000101 &
#141
0#
#142
1#
b0000000001000110 %
b00000000000000000000000001000110 &
#143
0#
#144
1#
b0000000001000111 %
b00000000000000000000000001000111 &
#145
0#
#146
1#
b0000000001001000 %
b00000000000000000000000001001000 &
#147
0#
#148
1#
b0000000001001001 %
b00000000000000000000000001001001 &
#149
0#
#150
1#
b0000000001001010 %
b00000000000000000000000001001010 &
#151
0#
#152
1#
b0000000001001011 %
b00000000000000000000000001001011 &
#153
0#
#154
1#
b0000000001001100 %
b00000000000000000000000001001100 &
#155
0#
#156
1#
b0000000001001101 %
b00000000000000000000000001001101 &
#157
0#
#158
1#
b0000000001001110 %
b00000000000000000000000001001110 &
#159
0#
#160
1#
b0000000001001111 %
b00000000000000000000000001001111 &
#161
0#
#162
1#
b0000000001010000 %
b00000000000000000000000001010000 &
#163
0#
#164
1#
b0000000001010001 %
b00000000000000000000000001010001 &
#165
0#
#166
1#
b0000000001010010 %
b00000000000000000000000001010010 &
#167
0#
#168
1#
b0000000001010011 %
b00000000000000000000000001010011 &
#169
0#
#170
1#
b0000000001010100 %
b00000000000000000000000001010100 &
#171
0#
#172
1#
b0000000001010101 %
b00000000000000000000000001010101 &
#173
0#
#174
1#
b0000000001010110 %
b00000000000000000000000001010110 &
#175
0#
#176
1#
b0000000001010111 %
b00000000000000000000000001010111 &
#177
0#
#178
1#
b0000000001011000 %
b00000000000000000000000001011000 &
#179
0#
#180
1#
b0000000001011001 %
b00000000000000000000000001011001 &
#181
0#
#182
1#
b0000000001011010 %
b00000000000000000000000001011010 &
#183
0#
#184
1#
b0000000001011011 %
b00000000000000000000000001011011 &
#185
0#
#186
1#
b0000000001011100 %
b00000000000000000000000001011100 &
#187
0#
#188
1#
b0000000001011101 %
b00000000000000000000000001011101 &
#189
0#
#190
1#
b0000000001011110 %
b00000000000000000000000001011110 &
#191
0#
#192
1#
b0000000001011111 %
b00000000000000000000000001011111 &
#193
0#
#194
1#
b0000000001100000 %
b00000000000000000000000001100000 &
#195
0#
#196
1#
b0000000001100001 %
b00000000000000000000000001100001 &
#197
0#
#198
1#
b0000000001100010 %
b00000000000000000000000001100010 &
#199
0#
#200
1#
b0000000001100011 %
b00000000000000000000000001100011 &
